{"_id":"6aH2RSVIXOMvKsoi","shortid":"SJkNJ_VQ7","name":"AddressesAndContacts(Excel)","recipe":"html-to-xlsx","engine":"handlebars","content":"<style>\n     table {\n        width: 100%; \n        /*border-collapse: collapse;*/\n    }\n    \n    /*thead > tr > th,  [border-bottom] {*/\n    /*    border-bottom: 1px solid black;*/\n    /*    padding-bottom:5px;*/\n    /*}*/\n    /*tfoot > tr > th, [border-top]{*/\n    /*    border-top: 1px  solid black;*/\n    /*    padding-top: 5px;*/\n    /*}*/\n    p {\n        font-size: 25;\n    }\n    \n    [center] {\n        text-align: center;\n    }\n    \n    [bold] {\n        font-weight: bold;\n    }\n    \n    [padding-20] {\n        padding-left : 20px;\n    }\n  [total]{\n      font-weight:bold;\n      font-size:25px;\n  }\n  [bot-border]{\n    border-bottom: 1px solid black;\n    font:10pt Verdana;\n    font-weight:bold;\n     \n  }\n  [padding-bot]{\n       padding-bottom:0px;\n       padding-left : 30px;\n  }\n  [top-margin]{\n      margin-top:35px;\n  }\n  /*thead { display: table-row-group } */\n</style>\n        <table style=\"text-align:left; font-family:Verdana; font-size:10pt;\">\n                  \n<thead style=\"text-align:center; font:10pt Verdana;\">\n\n        <tr>\n         <th colspan=\"13\" style=\"border-style:none; text-align:center; color:black; font-size:14pt;\">{{Single DataSource \"Company\"}} </th>\n        </tr>\n        <tr>\n        <th colspan=\"13\" style=\"border-style:none; text-align:center; color:black; font-size:12pt; padding-bottom:10px;\">Addresses and Contacts</th>\n        </tr>\n  \n \n  </thead>\n  <tr></tr><tr></tr>\n        \n           <tr style=\"visibility:hidden; font:10pt Verdana;\">\n                    <th padding-bot bot-border >Designation</th>\n                    <th padding-bot bot-border >Employee Code</th>\n                    <th padding-bot bot-border >Employee Name</th>\n                    <th padding-bot bot-border >Address Type</th>\n                    <th padding-bot bot-border >Address</th>\n                    <th padding-bot bot-border >City</th>\n                    <th padding-bot bot-border >Contact Number</th>\n                </tr>\n            \n            <tbody style=\"margin-top:-20px !important; Font:10pt Verdana;\">\n                {{#group DataSource by=\"Designation\"}}\n                <tr>\n                    <td padding-bot bold>{{ value }}</td>\n                    <td padding-bot ></td>\n                    <td padding-bot ></td>\n                    <td padding-bot ></td>\n                    <td padding-bot ></td>\n                    <td padding-bot ></td>\n                    <td padding-bot ></td>\n                    <td padding-bot ></td>\n                    <td padding-bot ></td>\n                    <td padding-bot ></td>\n                    <td padding-bot ></td>\n                    <td padding-bot ></td>\n                </tr>\n                {{#each items}}\n                <tr>\n                    <td padding-bot  style=\"padding-bottomd:0.5em;\"></td>\n                    <td padding-bot >{{ Code }}</td>\n                    <td padding-bot >{{ Name1 }}</td>\n                    <td padding-bot >{{ AddressType }}</td>\n                    <td padding-bot >{{ Address }}</td>\n                    <td padding-bot >{{ Area }}</td>\n                    <td padding-bot >{{ ContactNo }}</td>\n                </tr>\n                {{/each}}\n                {{/group}}\n            </tbody>\n        </table>\n  ","modificationDate":"2018-10-16T08:58:45.954Z","helpers":"","data":{"shortid":"HkAPCDV77"},"resources":{"items":[]}}